augur/__init__.py
augur/__main__.py
augur/__version__.py
augur/align.py
augur/ancestral.py
augur/argparse_.py
augur/clades.py
augur/debug.py
augur/distance.py
augur/errors.py
augur/export.py
augur/export_v1.py
augur/export_v2.py
augur/frequencies.py
augur/frequency_estimators.py
augur/index.py
augur/lbi.py
augur/mask.py
augur/merge.py
augur/parse.py
augur/read_file.py
augur/reconstruct_sequences.py
augur/refine.py
augur/sequence_traits.py
augur/subsample.py
augur/titer_model.py
augur/titers.py
augur/traits.py
augur/translate.py
augur/tree.py
augur/types.py
augur/utils.py
augur/validate.py
augur/validate_export.py
augur/version.py
augur/write_file.py
augur/curate/__init__.py
augur/curate/abbreviate_authors.py
augur/curate/apply_geolocation_rules.py
augur/curate/apply_record_annotations.py
augur/curate/format_dates.py
augur/curate/format_dates_directives.py
augur/curate/normalize_strings.py
augur/curate/parse_genbank_location.py
augur/curate/passthru.py
augur/curate/rename.py
augur/curate/titlecase.py
augur/curate/transform_strain_name.py
augur/data/__init__.py
augur/data/colors.tsv
augur/data/geolocation_rules.tsv
augur/data/lat_longs.tsv
augur/data/schema-annotations.json
augur/data/schema-auspice-config-v2.json
augur/data/schema-export-root-sequence.json
augur/data/schema-export-v1-meta.json
augur/data/schema-export-v1-tree.json
augur/data/schema-export-v2.json
augur/data/schema-frequencies.json
augur/data/schema-measurements-collection-config.json
augur/data/schema-measurements.json
augur/data/schema-subsample-config.json
augur/data/schema-tip-frequencies.json
augur/dates/__init__.py
augur/dates/ambiguous_date.py
augur/dates/errors.py
augur/filter/__init__.py
augur/filter/_run.py
augur/filter/arguments.py
augur/filter/constants.py
augur/filter/include_exclude_rules.py
augur/filter/io.py
augur/filter/subsample.py
augur/filter/validate_arguments.py
augur/filter/weights_file.py
augur/import_/__init__.py
augur/import_/beast.py
augur/io/__init__.py
augur/io/file.py
nextstrain_augur-32.1.0.dist-info/licenses/LICENSE.nextstrain-cli
nextstrain_augur-32.1.0.dist-info/licenses/LICENSE.nextstrain-ncov-ingest
nextstrain_augur-32.1.0.dist-info/licenses/LICENSE.txt
nextstrain_augur-32.1.0.dist-info/METADATA
nextstrain_augur-32.1.0.dist-info/WHEEL
nextstrain_augur-32.1.0.dist-info/entry_points.txt
nextstrain_augur-32.1.0.dist-info/top_level.txt
nextstrain_augur-32.1.0.dist-info/RECORD
